[
  {
    "id": "scoop",
    "name": "Scoop",
    "url": "https://scoop.co.za/scoop_pricelist.xml",
    "type": "xml",
    "enabled": true
  },
  {
    "id": "esquire",
    "name": "Esquire",
    "url": "https://api.esquire.co.za/api/DataFeed?u=blake@smartintegrate.co.za&p=Smart@1991&t=xml&m=10&o=ascending&r=RoundNone&rm=10&min=0",
    "type": "xml",
    "enabled": true
  },
  {
    "id": "pinnacle",
    "name": "Pinnacle",
    "url": "https://api.pinnacle.co.za/feed.xml",
    "type": "xml",
    "enabled": false
  },
  {
    "id": "mustek",
    "name": "Mustek",
    "url": "https://api.mustek.co.za/stock.xml",
    "type": "xml",
    "enabled": false
  }
]